dojo_google/__init__.py
dojo_google/beam/__init__.py
dojo_google/beam/transforms/__init__.py
dojo_google/beam/transforms/storage_file_contents.py
dojo_google/ml_engine/__init__.py
dojo_google/ml_engine/model.py
dojo_google/ml_engine/runners/__init__.py
dojo_google/ml_engine/runners/cloud.py
dojo_google/ml_engine/runners/direct.py
dojo_google/vanilla/__init__.py
dojo_google/vanilla/datasets/__init__.py
dojo_google/vanilla/datasets/storage_files.py
dojo_google/vanilla/datasets/storage_keys.py
dojo_google-0.0.21.dist-info/DESCRIPTION.rst
dojo_google-0.0.21.dist-info/METADATA
dojo_google-0.0.21.dist-info/RECORD
dojo_google-0.0.21.dist-info/WHEEL
dojo_google-0.0.21.dist-info/metadata.json
dojo_google-0.0.21.dist-info/top_level.txt
