Metadata-Version: 2.0
Name: dojo-google
Version: 0.0.21
Summary: Dojo transforms using Google APIs.
Home-page: https://dojo.dataup.me/
Author: Data Up
Author-email: dojo@dataup.me
License: UNKNOWN
Platform: UNKNOWN
Requires-Dist: dojo
Requires-Dist: google-api-python-client
Requires-Dist: retrying
